whook/__init__.py
whook/__main__.py
whook/cli.py
whook-0.0.1.dist-info/METADATA
whook-0.0.1.dist-info/WHEEL
whook-0.0.1.dist-info/entry_points.txt
whook-0.0.1.dist-info/top_level.txt
whook-0.0.1.dist-info/RECORD
