Metadata-Version: 2.1
Name: whook
Version: 0.0.1
Summary: A simple framework that can be used with Flask to build powerful webhooks.
Home-page: https://github.com/callope/whook/
Author: callope
License: UNKNOWN
Platform: UNKNOWN
Requires-Dist: attrs (==22.2.0)
Requires-Dist: certifi (==2022.12.7)
Requires-Dist: charset-normalizer (==3.0.1)
Requires-Dist: exceptiongroup (==1.1.0)
Requires-Dist: idna (==3.4)
Requires-Dist: iniconfig (==2.0.0)
Requires-Dist: packaging (==23.0)
Requires-Dist: pluggy (==1.0.0)
Requires-Dist: pytest (==7.2.1)
Requires-Dist: requests (==2.28.2)
Requires-Dist: tomli (==2.0.1)
Requires-Dist: urllib3 (==1.26.14)
Provides-Extra: test
Requires-Dist: attrs (==22.2.0) ; extra == 'test'
Requires-Dist: certifi (==2022.12.7) ; extra == 'test'
Requires-Dist: charset-normalizer (==3.0.1) ; extra == 'test'
Requires-Dist: exceptiongroup (==1.1.0) ; extra == 'test'
Requires-Dist: idna (==3.4) ; extra == 'test'
Requires-Dist: iniconfig (==2.0.0) ; extra == 'test'
Requires-Dist: packaging (==23.0) ; extra == 'test'
Requires-Dist: pluggy (==1.0.0) ; extra == 'test'
Requires-Dist: pytest (==7.2.1) ; extra == 'test'
Requires-Dist: requests (==2.28.2) ; extra == 'test'
Requires-Dist: tomli (==2.0.1) ; extra == 'test'
Requires-Dist: urllib3 (==1.26.14) ; extra == 'test'
